blazingplot/__init__.py
blazingplot/dashboard/__init__.py
blazingplot/dashboard/dashboard.py
blazingplot/dashboard/layout.py
blazingplot/tests/test_blazingplot.py
blazingplot/utils/__init__.py
blazingplot/utils/export.py
blazingplot/utils/performance.py
blazingplot/visualizations/__init__.py
blazingplot/visualizations/base.py
blazingplot-0.1.0.dist-info/licenses/LICENSE
blazingplot-0.1.0.dist-info/METADATA
blazingplot-0.1.0.dist-info/WHEEL
blazingplot-0.1.0.dist-info/top_level.txt
blazingplot-0.1.0.dist-info/RECORD
