Metadata-Version: 2.4
Name: blazingplot
Version: 0.1.0
Summary: A Fast and Fully Controlled Data Visualization Library
Author-email: BlazingPlot Team <info@blazingplot.com>
License: MIT
Project-URL: Homepage, https://github.com/username/blazingplot
Project-URL: Bug Tracker, https://github.com/username/blazingplot/issues
Classifier: Programming Language :: Python :: 3
Classifier: Programming Language :: Python :: 3.9
Classifier: Programming Language :: Python :: 3.10
Classifier: Programming Language :: Python :: 3.11
Classifier: License :: OSI Approved :: MIT License
Classifier: Operating System :: OS Independent
Classifier: Development Status :: 4 - Beta
Classifier: Intended Audience :: Developers
Classifier: Intended Audience :: Science/Research
Classifier: Topic :: Scientific/Engineering :: Visualization
Requires-Python: >=3.9
License-File: LICENSE
Requires-Dist: dash>=2.0.0
Requires-Dist: dash-bootstrap-components>=1.0.0
Requires-Dist: plotly>=5.0.0
Requires-Dist: polars>=0.15.0
Requires-Dist: pandas>=1.3.0
Requires-Dist: matplotlib>=3.4.0
Requires-Dist: numpy>=1.20.0
Requires-Dist: jupyter-dash>=0.4.0
Requires-Dist: ipython>=7.0.0
Provides-Extra: dev
Requires-Dist: pytest>=7.0.0; extra == "dev"
Requires-Dist: build; extra == "dev"
Requires-Dist: twine; extra == "dev"
Dynamic: license-file
